wagtailshowsimilar/__init__.py
wagtailshowsimilar/edit_handlers.py
wagtailshowsimilar/urls.py
wagtailshowsimilar/views.py
wagtailshowsimilar/locale/zh_Hant/LC_MESSAGES/django.mo
wagtailshowsimilar/locale/zh_Hant/LC_MESSAGES/django.po
wagtailshowsimilar/static/wagtailshowsimilar/showsimilar.js
wagtailshowsimilar/templates/wagtailshowsimilar/field.html
wagtailshowsimilar/templates/wagtailshowsimilar/field_panel.html
wagtail_showsimilar-0.1.0.dist-info/LICENSE
wagtail_showsimilar-0.1.0.dist-info/METADATA
wagtail_showsimilar-0.1.0.dist-info/WHEEL
wagtail_showsimilar-0.1.0.dist-info/top_level.txt
wagtail_showsimilar-0.1.0.dist-info/RECORD
