Metadata-Version: 2.1
Name: wagtail-showsimilar
Version: 0.1.0
Summary: wagtail input panel
Home-page: https://github.com/ongchi/wagtail-showsimilar
Author: ongchi
Author-email: ongchi@users.noreply.github.com
Project-URL: Bug Tracker, https://github.com/ongchi/wagtail-showsimilar/issues
Classifier: Environment :: Web Environment
Classifier: Intended Audience :: Developers
Classifier: License :: OSI Approved :: Apache Software License
Classifier: Operating System :: OS Independent
Classifier: Programming Language :: Python
Classifier: Programming Language :: Python :: 3.7
Classifier: Programming Language :: Python :: 3.8
Classifier: Programming Language :: Python :: 3.9
Classifier: Programming Language :: Python :: 3.10
Classifier: Programming Language :: Python :: 3.11
Classifier: Framework :: Django
Classifier: Framework :: Django :: 3.2
Classifier: Framework :: Django :: 4.0
Classifier: Framework :: Django :: 4.1
Classifier: Framework :: Wagtail
Classifier: Framework :: Wagtail :: 4
Classifier: Topic :: Internet :: WWW/HTTP
Classifier: Topic :: Internet :: WWW/HTTP :: Dynamic Content
Requires-Python: >=3.7
License-File: LICENSE
Requires-Dist: wagtail (>=4.0)
